examples/__init__.py
examples/cifar10/__init__.py
examples/cifar10/train.py
nolearn_utils/__init__.py
nolearn_utils/hooks.py
nolearn_utils/image_utils.py
nolearn_utils/iterators.py
nolearn_utils-0.3.1.dist-info/DESCRIPTION.rst
nolearn_utils-0.3.1.dist-info/METADATA
nolearn_utils-0.3.1.dist-info/RECORD
nolearn_utils-0.3.1.dist-info/WHEEL
nolearn_utils-0.3.1.dist-info/metadata.json
nolearn_utils-0.3.1.dist-info/pbr.json
nolearn_utils-0.3.1.dist-info/top_level.txt
