Metadata-Version: 2.0
Name: nolearn-utils
Version: 0.3.1
Summary: Utilities for nolearn.lasagne
Home-page: https://github.com/4Catalyzer/nolearn-utils
Author: Felix Lau
Author-email: felixlaumon@gmail.com
License: MIT
Platform: UNKNOWN
Classifier: Development Status :: 3 - Alpha
Classifier: Programming Language :: Python :: 2.7
Requires-Dist: joblib
Requires-Dist: numpy
Requires-Dist: scikit-image
Requires-Dist: six
Provides-Extra: docs
Requires-Dist: Sphinx; extra == 'docs'
Provides-Extra: examples
Requires-Dist: Lasagne; extra == 'examples'
Requires-Dist: nolearn; extra == 'examples'
Provides-Extra: testing
Requires-Dist: mock; extra == 'testing'
Requires-Dist: pytest; extra == 'testing'
Requires-Dist: pytest-cov; extra == 'testing'
Requires-Dist: pytest-pep8; extra == 'testing'
